LICENSE
MANIFEST.in
README.md
setup.cfg
setup.py
suap_ead/__init__.py
suap_ead/apps.py
suap_ead/context_processors.py
suap_ead/fields.py
suap_ead/modules.py
suap_ead/template_settings.py
suap_ead/urls.py
suap_ead/views.py
suap_ead/wsgi.py
suap_ead.egg-info/PKG-INFO
suap_ead.egg-info/SOURCES.txt
suap_ead.egg-info/dependency_links.txt
suap_ead.egg-info/requires.txt
suap_ead.egg-info/top_level.txt
suap_ead/auth/__init__.py
suap_ead/auth/drf.py
suap_ead/auth/jwt.py
suap_ead/auth/oauth2.py
suap_ead/static/css/autocomplete.css
suap_ead/static/css/base.css
suap_ead/static/css/bootstrap-grid.css
suap_ead/static/css/bootstrap-grid.css.map
suap_ead/static/css/bootstrap-grid.min.css
suap_ead/static/css/bootstrap-grid.min.css.map
suap_ead/static/css/bootstrap-reboot.css
suap_ead/static/css/bootstrap-reboot.css.map
suap_ead/static/css/bootstrap-reboot.min.css
suap_ead/static/css/bootstrap-reboot.min.css.map
suap_ead/static/css/bootstrap.css
suap_ead/static/css/bootstrap.css.map
suap_ead/static/css/bootstrap.min.css
suap_ead/static/css/bootstrap.min.css.map
suap_ead/static/css/changelists.css
suap_ead/static/css/dashboard.css
suap_ead/static/css/fonts.css
suap_ead/static/css/forms.css
suap_ead/static/css/general.css
suap_ead/static/css/login.css
suap_ead/static/css/responsive.css
suap_ead/static/css/responsive_rtl.css
suap_ead/static/css/rtl.css
suap_ead/static/css/vue-material.min.css
suap_ead/static/css/vuetify.min.css
suap_ead/static/css/widgets.css
suap_ead/static/css/ava_ead_alternative/base.css
suap_ead/static/css/ava_ead_default/base.css
suap_ead/static/css/contrast/base.css
suap_ead/static/css/coral/base.css
suap_ead/static/css/dark/base.css
suap_ead/static/css/golden/base.css
suap_ead/static/css/highcontrast/base.css
suap_ead/static/css/navy/base.css
suap_ead/static/css/purple/base.css
suap_ead/static/css/suap_ead_alternative/base.css
suap_ead/static/css/suap_ead_default/base.css
suap_ead/static/css/vendor/select2/LICENSE-SELECT2.md
suap_ead/static/css/vendor/select2/select2.css
suap_ead/static/css/vendor/select2/select2.min.css
suap_ead/static/favicons/README.md
suap_ead/static/favicons/android-chrome-192x192.png
