Metadata-Version: 2.1
Name: suap-ead
Version: 0.1.12
Summary: Utils and theme classes for SUAP-EAD project services
Home-page: https://github.com/suap-ead/lib_suap_ead
Author: Kelson da Costa Medeiros, Luiz Antonio Freitas de Assis
Author-email: kelsoncm@gmail.com, luizvpc@gmail.com
License: MIT
Download-URL: https://github.com/suap-ead/lib_suap_ead/releases/tag/0.1.12
Keywords: SUAP,EAD,complemento,JWT,Django,Auth,SSO,client,Theme
Platform: UNKNOWN
Classifier: Programming Language :: Python :: 3
Classifier: License :: OSI Approved :: MIT License
Classifier: Operating System :: OS Independent
License-File: LICENSE
